{"base_args": {"logprobs": 20, "max_tokens": 1200}, "extend_args": {"temperature": 1, "n": 30, "max_tokens": 512}, "ans_args": {}, "tok_depth": 1200, "p_thresh": 0.05, "row": {"question": "In how many ways can 5 different candies be distributed among 4 children? (Children could get 0 candies or more than one candy)", "options": ["A)4^5", "B)5^4", "C)5!", "D)4!", "E)4!*5!"], "rationale": "There are in total 5 candies. Let's say A,B,C,D and E.\nCandy A can be distributed among any 4 children. So, there are 4 ways of distributing candy A.\nsimilarly candy B,C,D and E can be distributed in 4 ways.\nSo total ways of distribution is\n4*4*4*4*4 = 4^5.\nANS:A", "correct": "A", "q_len": 127, "a_len": 263, "index": 41}}