{"base_args": {"logprobs": 20, "max_tokens": 1200}, "extend_args": {"temperature": 1, "n": 30, "max_tokens": 512}, "ans_args": {}, "tok_depth": 1200, "p_thresh": 0.05, "row": {"question": "If a jewelry store wants to sell a necklace for $179.95 next week at a 50% off sale, how much is the price of the necklace this week?", "options": ["A)$71.98", "B)$251.93", "C)$287.92", "D)$359.90", "E)$449.88"], "rationale": "Let the price of necklace this week = p\nDiscount for next week = 50%\n(1-50/100)p = 179.95\n=>(50/100) p = 179.95\n=> p = 359.90\nAnswer D", "correct": "D", "q_len": 133, "a_len": 134, "index": 250}}